setup.py
MiniLED/MiniLED.py
MiniLED/__init__.py
MiniLED.egg-info/PKG-INFO
MiniLED.egg-info/SOURCES.txt
MiniLED.egg-info/dependency_links.txt
MiniLED.egg-info/requires.txt
MiniLED.egg-info/top_level.txt