Metadata-Version: 1.0
Name: MiniLED
Version: 0-1
Summary: A python API to display text/images to small LED badges and signs
Home-page: https://github.com/robertf224/MiniLED/
Author: Robert Fidler
Author-email: robertf224@gmail.com
License: UNKNOWN
Keywords: led,sign,badge
Platform: UNKNOWN
